{
  "nodes": [
    {
      "id": "6c67fa01f7",
      "position": {
        "x": 5,
        "y": -25
      }
    },
    {
      "id": "d0ab45bcf6",
      "position": {
        "x": 322,
        "y": -56
      }
    },
    {
      "id": "a862a707f5",
      "position": {
        "x": 660,
        "y": -55
      }
    },
    {
      "id": "1f916f660a",
      "position": {
        "x": 950,
        "y": -50
      }
    },
    {
      "id": "c393f08026",
      "position": {
        "x": 327,
        "y": 204
      }
    },
    {
      "id": "cedadbbe58",
      "position": {
        "x": 670,
        "y": 205
      }
    },
    {
      "id": "71989b02a2",
      "position": {
        "x": 1265,
        "y": -15
      }
    }
  ],
  "links": [
    {
      "source": "1f916f660a",
      "sourcePort": "out0",
      "target": "71989b02a2",
      "points": [
        {
          "x": 1150,
          "y": -6
        },
        {
          "x": 1265,
          "y": 3
        }
      ]
    },
    {
      "source": "1f916f660a",
      "sourcePort": "out1",
      "target": "d0ab45bcf6",
      "points": [
        {
          "x": 1150,
          "y": 24
        },
        {
          "x": 1205,
          "y": -85
        },
        {
          "x": 280,
          "y": -90
        },
        {
          "x": 323,
          "y": -38
        }
      ]
    },
    {
      "source": "6c67fa01f7",
      "sourcePort": "out0",
      "target": "d0ab45bcf6",
      "points": [
        {
          "x": 205,
          "y": 19
        },
        {
          "x": 323,
          "y": -38
        }
      ]
    },
    {
      "source": "a862a707f5",
      "sourcePort": "out0",
      "target": "1f916f660a",
      "points": [
        {
          "x": 860,
          "y": 78
        },
        {
          "x": 950,
          "y": -32
        }
      ]
    },
    {
      "source": "a862a707f5",
      "sourcePort": "out1",
      "target": "cedadbbe58",
      "points": [
        {
          "x": 860,
          "y": 109
        },
        {
          "x": 895,
          "y": 150
        },
        {
          "x": 630,
          "y": 185
        },
        {
          "x": 670,
          "y": 223
        }
      ]
    },
    {
      "source": "c393f08026",
      "sourcePort": "out0",
      "target": "d0ab45bcf6",
      "points": [
        {
          "x": 527,
          "y": 303
        },
        {
          "x": 570,
          "y": 185
        },
        {
          "x": 275,
          "y": 145
        },
        {
          "x": 323,
          "y": -38
        }
      ]
    },
    {
      "source": "cedadbbe58",
      "sourcePort": "out0",
      "target": "a862a707f5",
      "points": [
        {
          "x": 870,
          "y": 304
        },
        {
          "x": 895,
          "y": 185
        },
        {
          "x": 625,
          "y": 150
        },
        {
          "x": 660,
          "y": -37
        }
      ]
    },
    {
      "source": "d0ab45bcf6",
      "sourcePort": "out0",
      "target": "a862a707f5",
      "points": [
        {
          "x": 522,
          "y": 77
        },
        {
          "x": 660,
          "y": -37
        }
      ]
    },
    {
      "source": "d0ab45bcf6",
      "sourcePort": "out1",
      "target": "c393f08026",
      "points": [
        {
          "x": 522,
          "y": 108
        },
        {
          "x": 570,
          "y": 145
        },
        {
          "x": 275,
          "y": 185
        },
        {
          "x": 328,
          "y": 222
        }
      ]
    }
  ]
}